segno/__init__.py
segno/__init__.pyi
segno/cli.py
segno/consts.py
segno/encoder.py
segno/helpers.py
segno/helpers.pyi
segno/py.typed
segno/utils.py
segno/writers.py
segno-1.6.5.data/data/usr/share/man/man1/segno.1
segno-1.6.5.dist-info/entry_points.txt
segno-1.6.5.dist-info/licenses/LICENSE
segno-1.6.5.dist-info/WHEEL
segno-1.6.5.dist-info/METADATA
segno-1.6.5.dist-info/RECORD
