Metadata-Version: 2.4
Name: segno
Version: 1.6.5
Summary: QR Code and Micro QR Code generator for Python
Keywords: QR Code,Micro QR Code,ISO/IEC 18004,ISO/IEC 18004:2006(E),ISO/IEC 18004:2015(E),qrcode,QR,barcode,matrix,2D
Author-email: Lars Heuer <heuer@semagia.com>
Requires-Python: >=3.5
Classifier: Development Status :: 5 - Production/Stable
Classifier: Intended Audience :: Developers
Classifier: License :: OSI Approved :: BSD License
Classifier: Operating System :: OS Independent
Classifier: Programming Language :: Python
Classifier: Programming Language :: Python :: 3
Classifier: Programming Language :: Python :: 3 :: Only
Classifier: Topic :: Multimedia :: Graphics
Classifier: Topic :: Printing
Classifier: Topic :: Software Development :: Libraries :: Python Modules
Classifier: Topic :: Utilities
License-File: LICENSE
Requires-Dist: importlib-metadata>=3.6.0; python_version < '3.10'
Project-URL: Changes, https://github.com/heuer/segno/blob/master/CHANGES.rst
Project-URL: Documentation, https://segno.readthedocs.io/
Project-URL: Homepage, https://github.com/heuer/segno/
Project-URL: Issue tracker, https://github.com/heuer/segno/issues/
